CHANGELOG
LICENSE
MANIFEST.in
NOTICE
README.md
UBJSON-Specification.md
ez_setup.py
setup.py
py_ubjson.egg-info/PKG-INFO
py_ubjson.egg-info/SOURCES.txt
py_ubjson.egg-info/dependency_links.txt
py_ubjson.egg-info/not-zip-safe
py_ubjson.egg-info/top_level.txt
src/_ubjson.c
src/common.h
src/decoder.c
src/decoder.h
src/encoder.c
src/encoder.h
src/markers.h
src/python_funcs.c
src/python_funcs.h
test/test.py
ubjson/__init__.py
ubjson/__main__.py
ubjson/compat.py
ubjson/decoder.py
ubjson/encoder.py
ubjson/markers.py